quicksampleTest.py
quicksampleTest-0.0.1.dist-info/LICENSE
quicksampleTest-0.0.1.dist-info/METADATA
quicksampleTest-0.0.1.dist-info/WHEEL
quicksampleTest-0.0.1.dist-info/top_level.txt
quicksampleTest-0.0.1.dist-info/RECORD
